scikit_digital_health-0.17.9.dist-info/RECORD
scikit_digital_health-0.17.9.dist-info/LICENSE
scikit_digital_health-0.17.9.dist-info/WHEEL
scikit_digital_health-0.17.9.dist-info/METADATA
skdh/__init__.py
skdh/pipeline.py
skdh/base.py
skdh/context/ambulation_classification.py
skdh/context/gait_classification.py
skdh/context/__init__.py
skdh/context/motion_detect.py
skdh/context/model/lgbm_gait_classifier_no-stairs_20hz.lgbm
skdh/context/model/ambulation_model.txt
skdh/context/model/__init__.py
skdh/context/model/gait_final_features.json
skdh/context/model/lgbm_gait_classifier_no-stairs_50hz.lgbm
skdh/sit2stand/detector.py
skdh/sit2stand/__init__.py
skdh/sit2stand/sit2stand.py
skdh/sleep/utility.py
skdh/sleep/tso.py
skdh/sleep/__init__.py
skdh/sleep/sleep_classification.py
skdh/sleep/sleep.py
skdh/sleep/endpoints.py
skdh/activity/metrics.py
skdh/activity/cutpoints.py
skdh/activity/utility.py
skdh/activity/__init__.py
skdh/activity/core.py
skdh/activity/endpoints.py
skdh/io/multireader.py
skdh/io/__init__.py
skdh/io/geneactiv.py
skdh/io/numpy_compressed.py
skdh/io/apdm.py
skdh/io/csv.py
skdh/io/empatica.py
skdh/io/axivity.py
skdh/io/base.py
skdh/io/_extensions/__init__.py
skdh/io/_extensions/read.cpython-39-darwin.so
skdh/features/__init__.py
skdh/features/core.py
skdh/features/lib/frequency.py
skdh/features/lib/misc.py
skdh/features/lib/multi_axis.py
skdh/features/lib/moments.py
skdh/features/lib/__init__.py
skdh/features/lib/smoothness.py
skdh/features/lib/wavelet.py
skdh/features/lib/statistics.py
skdh/features/lib/entropy.py
skdh/features/lib/extensions/smoothness.cpython-39-darwin.so
skdh/features/lib/extensions/misc_features.cpython-39-darwin.so
skdh/features/lib/extensions/_utility.cpython-39-darwin.so
skdh/features/lib/extensions/__init__.py
skdh/features/lib/extensions/frequency.cpython-39-darwin.so
skdh/features/lib/extensions/statistics.cpython-39-darwin.so
skdh/features/lib/extensions/entropy.cpython-39-darwin.so
skdh/gait_old/get_strides.py
skdh/gait_old/__init__.py
skdh/gait_old/get_gait_classification.py
skdh/gait_old/get_gait_events.py
skdh/gait_old/get_gait_bouts.py
