Metadata-Version: 2.1
Name: scikit-digital-health
Version: 0.17.9
Summary: Python general purpose human motion inertial data processing package.
Author-Email: Lukas Adamowicz <lukas.adamowicz@pfizer.com>
License: MIT License
Classifier: Development Status :: 4 - Beta
Classifier: License :: OSI Approved :: MIT License
Classifier: Programming Language :: Python
Classifier: Programming Language :: Python :: 3.9
Classifier: Programming Language :: Python :: 3.10
Classifier: Programming Language :: Fortran
Classifier: Programming Language :: C
Classifier: Intended Audience :: Science/Research
Classifier: Intended Audience :: Developers
Classifier: Topic :: Software Development
Classifier: Topic :: Scientific/Engineering
Classifier: Operating System :: MacOS
Classifier: Operating System :: POSIX :: Linux
Project-URL: homepage, https://github.com/pfizer-opensource/scikit-digital-health
Project-URL: documentation, https://scikit-digital-health.readthedocs.io/en/latest/
Requires-Python: >=3.9
Requires-Dist: numpy>=1.25.0
Requires-Dist: scipy>=1.12.0
Requires-Dist: pandas>=1.0.0
Requires-Dist: lightgbm>=2.3.0
Requires-Dist: pywavelets
Requires-Dist: scikit-learn
Requires-Dist: h5py
Requires-Dist: matplotlib
Requires-Dist: packaging
Requires-Dist: pyyaml
Requires-Dist: avro
Provides-Extra: dev
Requires-Dist: pytest; extra == "dev"
Requires-Dist: coverage; extra == "dev"
Requires-Dist: psutil; extra == "dev"
Requires-Dist: numpy>=2.0.0rc1; extra == "dev"
Provides-Extra: actions
Requires-Dist: flake8; extra == "actions"
Requires-Dist: wheel; extra == "actions"
Provides-Extra: docs
Requires-Dist: numpydoc; extra == "docs"
Requires-Dist: sphinx>=2.2.0; extra == "docs"
Requires-Dist: pydata-sphinx-theme; extra == "docs"
Requires-Dist: sphinx-design; extra == "docs"
